{
  "annotations": {
    "changelogDate": "20260108164541"
  },
  "applications": "*",
  "dto": "mapstruct",
  "fields": [
    {
      "fieldName": "isCompleted",
      "fieldType": "Boolean",
      "fieldValidateRules": ["required"]
    },
    {
      "fieldName": "updatedAt",
      "fieldType": "Instant",
      "fieldValidateRules": ["required"]
    }
  ],
  "name": "Progress",
  "relationships": [
    {
      "otherEntityName": "userProfile",
      "otherEntityRelationshipName": "progresses",
      "relationshipName": "userProfile",
      "relationshipSide": "right",
      "relationshipType": "many-to-one",
      "relationshipValidateRules": "required"
    },
    {
      "otherEntityName": "unit",
      "otherEntityRelationshipName": "progresses",
      "relationshipName": "unit",
      "relationshipSide": "right",
      "relationshipType": "many-to-one",
      "relationshipValidateRules": "required"
    }
  ],
  "searchEngine": "no",
  "service": "serviceClass"
}
